ft_package_juhoh/__init__.py
ft_package_juhoh/ft_package.py
ft_package_juhoh-0.0.4.dist-info/LICENSE
ft_package_juhoh-0.0.4.dist-info/METADATA
ft_package_juhoh-0.0.4.dist-info/WHEEL
ft_package_juhoh-0.0.4.dist-info/top_level.txt
ft_package_juhoh-0.0.4.dist-info/RECORD
